<checks>
<result><category>media-plugins</category><package>audacious-dumb</package><class>PkgMetadataXmlInvalidProjectError</class><msg>media-plugins/audacious-dumb metadata.xml &lt;maintainer/&gt; references invalid project 'sound@gentoo.org'</msg></result>
<result><category>media-plugins</category><package>audacious-plugins</package><class>PkgMetadataXmlInvalidProjectError</class><msg>media-plugins/audacious-plugins metadata.xml &lt;maintainer/&gt; references invalid project 'sound@gentoo.org'</msg></result>
<result><category>media-plugins</category><package>audacious-plugins</package><version>2.5.4</version><class>VulnerablePackage</class><msg>vulnerable via glsa(201203-14) ( ver &lt; 3.1 ), keywords ('alpha', 'amd64', 'amd64-linux', 'hppa', 'ppc', 'ppc64', 'sparc', 'x86', 'x86-fbsd', 'x86-freebsd', 'x86-interix', 'x86-linux')</msg></result>
<result><category>media-plugins</category><package>audacious-plugins</package><version>3.6.2-r1</version><class>DroppedKeyword</class><msg>keywords dropped: sparc</msg></result>
<result><category>media-plugins</category><package>emotion_generic_players</package><class>PkgMetadataXmlInvalidProjectError</class><msg>media-plugins/emotion_generic_players metadata.xml &lt;maintainer/&gt; references invalid project 'enlightenment@gentoo.org'</msg></result>
<result><category>media-plugins</category><package>evas_generic_loaders</package><class>PkgMetadataXmlInvalidProjectError</class><msg>media-plugins/evas_generic_loaders metadata.xml &lt;maintainer/&gt; references invalid project 'enlightenment@gentoo.org'</msg></result>
<result><category>media-plugins</category><package>frei0r-plugins</package><class>PkgMetadataXmlInvalidProjectError</class><msg>media-plugins/frei0r-plugins metadata.xml &lt;maintainer/&gt; references invalid project 'media-video@gentoo.org'</msg></result>
<result><category>media-plugins</category><package>gkrellmpc</package><class>PkgMetadataXmlInvalidProjectError</class><msg>media-plugins/gkrellmpc metadata.xml &lt;maintainer/&gt; references invalid project 'sound@gentoo.org'</msg></result>
<result><category>media-plugins</category><package>gmpc-alarm</package><class>PkgMetadataXmlInvalidProjectError</class><msg>media-plugins/gmpc-alarm metadata.xml &lt;maintainer/&gt; references invalid project 'sound@gentoo.org'</msg></result>
<result><category>media-plugins</category><package>gmpc-albumview</package><class>PkgMetadataXmlInvalidProjectError</class><msg>media-plugins/gmpc-albumview metadata.xml &lt;maintainer/&gt; references invalid project 'sound@gentoo.org'</msg></result>
<result><category>media-plugins</category><package>gmpc-avahi</package><class>PkgMetadataXmlInvalidProjectError</class><msg>media-plugins/gmpc-avahi metadata.xml &lt;maintainer/&gt; references invalid project 'sound@gentoo.org'</msg></result>
<result><category>media-plugins</category><package>gmpc-awn</package><class>PkgMetadataXmlInvalidProjectError</class><msg>media-plugins/gmpc-awn metadata.xml &lt;maintainer/&gt; references invalid project 'sound@gentoo.org'</msg></result>
<result><category>media-plugins</category><package>gmpc-discogs</package><class>PkgMetadataXmlInvalidProjectError</class><msg>media-plugins/gmpc-discogs metadata.xml &lt;maintainer/&gt; references invalid project 'sound@gentoo.org'</msg></result>
<result><category>media-plugins</category><package>gmpc-extraplaylist</package><class>PkgMetadataXmlInvalidProjectError</class><msg>media-plugins/gmpc-extraplaylist metadata.xml &lt;maintainer/&gt; references invalid project 'sound@gentoo.org'</msg></result>
<result><category>media-plugins</category><package>gmpc-jamendo</package><class>PkgMetadataXmlInvalidProjectError</class><msg>media-plugins/gmpc-jamendo metadata.xml &lt;maintainer/&gt; references invalid project 'sound@gentoo.org'</msg></result>
<result><category>media-plugins</category><package>gmpc-last-fm</package><class>PkgMetadataXmlInvalidProjectError</class><msg>media-plugins/gmpc-last-fm metadata.xml &lt;maintainer/&gt; references invalid project 'sound@gentoo.org'</msg></result>
<result><category>media-plugins</category><package>gmpc-libnotify</package><class>PkgMetadataXmlInvalidProjectError</class><msg>media-plugins/gmpc-libnotify metadata.xml &lt;maintainer/&gt; references invalid project 'sound@gentoo.org'</msg></result>
<result><category>media-plugins</category><package>gmpc-lyrics</package><class>PkgMetadataXmlInvalidProjectError</class><msg>media-plugins/gmpc-lyrics metadata.xml &lt;maintainer/&gt; references invalid project 'sound@gentoo.org'</msg></result>
<result><category>media-plugins</category><package>gmpc-lyricwiki</package><class>PkgMetadataXmlInvalidProjectError</class><msg>media-plugins/gmpc-lyricwiki metadata.xml &lt;maintainer/&gt; references invalid project 'sound@gentoo.org'</msg></result>
<result><category>media-plugins</category><package>gmpc-magnatune</package><class>PkgMetadataXmlInvalidProjectError</class><msg>media-plugins/gmpc-magnatune metadata.xml &lt;maintainer/&gt; references invalid project 'sound@gentoo.org'</msg></result>
<result><category>media-plugins</category><package>gmpc-mdcover</package><class>PkgMetadataXmlInvalidProjectError</class><msg>media-plugins/gmpc-mdcover metadata.xml &lt;maintainer/&gt; references invalid project 'sound@gentoo.org'</msg></result>
<result><category>media-plugins</category><package>gmpc-mmkeys</package><class>PkgMetadataXmlInvalidProjectError</class><msg>media-plugins/gmpc-mmkeys metadata.xml &lt;maintainer/&gt; references invalid project 'sound@gentoo.org'</msg></result>
<result><category>media-plugins</category><package>gmpc-mserver</package><class>PkgMetadataXmlInvalidProjectError</class><msg>media-plugins/gmpc-mserver metadata.xml &lt;maintainer/&gt; references invalid project 'sound@gentoo.org'</msg></result>
<result><category>media-plugins</category><package>gmpc-playlistsort</package><class>PkgMetadataXmlInvalidProjectError</class><msg>media-plugins/gmpc-playlistsort metadata.xml &lt;maintainer/&gt; references invalid project 'sound@gentoo.org'</msg></result>
<result><category>media-plugins</category><package>gmpc-shout</package><class>PkgMetadataXmlInvalidProjectError</class><msg>media-plugins/gmpc-shout metadata.xml &lt;maintainer/&gt; references invalid project 'sound@gentoo.org'</msg></result>
<result><category>media-plugins</category><package>gmpc-tagedit</package><class>PkgMetadataXmlInvalidProjectError</class><msg>media-plugins/gmpc-tagedit metadata.xml &lt;maintainer/&gt; references invalid project 'sound@gentoo.org'</msg></result>
<result><category>media-plugins</category><package>gmpc-wikipedia</package><class>PkgMetadataXmlInvalidProjectError</class><msg>media-plugins/gmpc-wikipedia metadata.xml &lt;maintainer/&gt; references invalid project 'sound@gentoo.org'</msg></result>
<result><category>media-plugins</category><package>grilo-plugins</package><class>PkgMetadataXmlInvalidProjectError</class><msg>media-plugins/grilo-plugins metadata.xml &lt;maintainer/&gt; references invalid project 'gnome@gentoo.org'</msg></result>
<result><category>media-plugins</category><package>grilo-plugins</package><version>0.2.17</version><class>NonExistentDeps</class><msg>depset depends: nonexistent dep: [ &gt;=dev-lang/lua-5.3 ]</msg></result>
<result><category>media-plugins</category><package>grilo-plugins</package><version>0.2.17</version><class>NonExistentDeps</class><msg>depset rdepends: nonexistent dep: [ &gt;=dev-lang/lua-5.3 ]</msg></result>
<result><category>media-plugins</category><package>grilo-plugins</package><version>0.3.2</version><class>NonExistentDeps</class><msg>depset depends: nonexistent dep: [ &gt;=dev-lang/lua-5.3 ]</msg></result>
<result><category>media-plugins</category><package>grilo-plugins</package><version>0.3.2</version><class>NonExistentDeps</class><msg>depset rdepends: nonexistent dep: [ &gt;=dev-lang/lua-5.3 ]</msg></result>
<result><category>media-plugins</category><package>grilo-plugins</package><version>0.2.17</version><class>DroppedKeyword</class><msg>keywords dropped: arm, ia64</msg></result>
<result><category>media-plugins</category><package>gst-plugins-dts</package><version>1.6.3</version><class>DroppedKeyword</class><msg>keywords dropped: arm</msg></result>
<result><category>media-plugins</category><package>gst-plugins-dv</package><version>1.4.5</version><class>DroppedKeyword</class><msg>keywords dropped: arm</msg></result>
<result><category>media-plugins</category><package>gst-plugins-libnice</package><class>PkgMetadataXmlInvalidProjectError</class><msg>media-plugins/gst-plugins-libnice metadata.xml &lt;maintainer/&gt; references invalid project 'gnome@gentoo.org'</msg></result>
<result><category>media-plugins</category><package>gst-plugins-libvisual</package><version>1.4.5</version><class>DroppedKeyword</class><msg>keywords dropped: arm</msg></result>
<result><category>media-plugins</category><package>gst-plugins-meta</package><class>PkgMetadataXmlInvalidProjectError</class><msg>media-plugins/gst-plugins-meta metadata.xml &lt;maintainer/&gt; references invalid project 'gnome@gentoo.org'</msg></result>
<result><category>media-plugins</category><package>gst-plugins-mplex</package><version>1.4.5</version><class>DroppedKeyword</class><msg>keywords dropped: arm</msg></result>
<result><category>media-plugins</category><package>gst-plugins-shout2</package><version>1.4.5</version><class>DroppedKeyword</class><msg>keywords dropped: sh</msg></result>
<result><category>media-plugins</category><package>gst-plugins-wavpack</package><version>1.4.5</version><class>DroppedKeyword</class><msg>keywords dropped: arm</msg></result>
<result><category>media-plugins</category><package>hexter</package><version>1.0.3</version><class>MissingSlotDep</class><msg>'sys-libs/ncurses' matches more than one slot: [ 0, 5 ]</msg></result>
<result><category>media-plugins</category><package>imlib2_loaders</package><class>PkgMetadataXmlInvalidProjectError</class><msg>media-plugins/imlib2_loaders metadata.xml &lt;maintainer/&gt; references invalid project 'enlightenment@gentoo.org'</msg></result>
<result><category>media-plugins</category><package>kipi-plugins</package><class>PkgMetadataXmlInvalidProjectError</class><msg>media-plugins/kipi-plugins metadata.xml &lt;maintainer/&gt; references invalid project 'kde@gentoo.org'</msg></result>
<result><category>media-plugins</category><package>kipi-plugins</package><version>4.4.0</version><class>MissingSlotDep</class><msg>'media-libs/tiff' matches more than one slot: [ 0, 3 ]</msg></result>
<result><category>media-plugins</category><package>kipi-plugins</package><version>4.4.0</version><class>MissingSlotDep</class><msg>'virtual/jpeg' matches more than one slot: [ 0, 62 ]</msg></result>
<result><category>media-plugins</category><package>kipi-plugins</package><version>5.1.0</version><class>NonExistentDeps</class><msg>depset depends: nonexistent deps: [ net-libs/libmediawiki:5, net-libs/libkvkontakte:5 ]</msg></result>
<result><category>media-plugins</category><package>kipi-plugins</package><version>5.1.0</version><class>NonExistentDeps</class><msg>depset rdepends: nonexistent deps: [ net-libs/libmediawiki:5, net-libs/libkvkontakte:5 ]</msg></result>
<result><category>media-plugins</category><package>libvisual-plugins</package><class>PkgMetadataXmlInvalidProjectError</class><msg>media-plugins/libvisual-plugins metadata.xml &lt;maintainer/&gt; references invalid project 'sound@gentoo.org'</msg></result>
<result><category>media-plugins</category><package>libvisual-projectm</package><class>PkgMetadataXmlInvalidProjectError</class><msg>media-plugins/libvisual-projectm metadata.xml &lt;maintainer/&gt; references invalid project 'sound@gentoo.org'</msg></result>
<result><category>media-plugins</category><package>live</package><class>PkgMetadataXmlInvalidProjectError</class><msg>media-plugins/live metadata.xml &lt;maintainer/&gt; references invalid project 'media-video@gentoo.org'</msg></result>
<result><category>media-plugins</category><package>mythplugins</package><version>0.27_p20140321-r1</version><class>NonExistentDeps</class><msg>depset depends: nonexistent dep: [ =dev-lang/python-2.6* ]</msg></result>
<result><category>media-plugins</category><package>mythplugins</package><version>0.27_p20140321-r1</version><class>NonExistentDeps</class><msg>depset rdepends: nonexistent dep: [ =dev-lang/python-2.6* ]</msg></result>
<result><category>media-plugins</category><package>npapi-vlc</package><class>PkgMetadataXmlInvalidProjectError</class><msg>media-plugins/npapi-vlc metadata.xml &lt;maintainer/&gt; references invalid project 'media-video@gentoo.org'</msg></result>
<result><category>media-plugins</category><package>qmmp-plugin-pack</package><class>PkgMetadataXmlInvalidProjectError</class><msg>media-plugins/qmmp-plugin-pack metadata.xml &lt;maintainer/&gt; references invalid project 'sound@gentoo.org'</msg></result>
<result><category>media-plugins</category><package>swh-plugins</package><class>SizeViolation</class><msg>"files/swh-plugins-0.4.15-glibc-2.10.patch" exceeds 20k in size; 26.8 KiB total</msg></result>
<result><category>dev-lang</category><package>ats</package><version>0.2.9</version><class>MissingSlotDep</class><msg>'dev-libs/gmp' matches more than one slot: [ 0, 3 ]</msg></result>
<result><category>dev-lang</category><package>ats</package><version>0.2.9</version><class>MissingSlotDep</class><msg>'dev-libs/glib' matches more than one slot: [ 1, 2 ]</msg></result>
<result><category>dev-lang</category><package>ats</package><version>0.2.9</version><class>MissingSlotDep</class><msg>'sys-libs/ncurses' matches more than one slot: [ 0, 5 ]</msg></result>
<result><category>dev-lang</category><package>fpc</package><version>3.0.0</version><class>DroppedKeyword</class><msg>keywords dropped: arm, ppc</msg></result>
<result><category>dev-lang</category><package>ghc</package><version>7.4.2</version><class>MissingSlotDep</class><msg>'&gt;=sys-devel/binutils-2.17' matches more than one slot: [ 2.21.1, 2.22, 2.23.2, 2.24, 2.25, 2.25.1, 2.26.1, git ]</msg></result>
<result><category>dev-lang</category><package>ghc</package><version>7.4.2</version><class>MissingSlotDep</class><msg>'&gt;=sys-devel/gcc-2.95.3' matches more than one slot: [ 2.95.3, 3.3.6, 3.4.6, 4.0.4, 4.1.2, 4.2.4, 4.3.6, 4.4.7, 4.5.4, 4.6.4, 4.7.4, 4.8.5, 4.9.3, 4.9.4, 5.1.0, 5.2.0, 5.3.0, 5.4.0 ]</msg></result>
<result><category>dev-lang</category><package>ghc</package><version>7.6.3-r1</version><class>MissingSlotDep</class><msg>'&gt;=sys-devel/binutils-2.17' matches more than one slot: [ 2.21.1, 2.22, 2.23.2, 2.24, 2.25, 2.25.1, 2.26.1, git ]</msg></result>
<result><category>dev-lang</category><package>ghc</package><version>7.6.3-r1</version><class>MissingSlotDep</class><msg>'&gt;=sys-devel/gcc-2.95.3' matches more than one slot: [ 2.95.3, 3.3.6, 3.4.6, 4.0.4, 4.1.2, 4.2.4, 4.3.6, 4.4.7, 4.5.4, 4.6.4, 4.7.4, 4.8.5, 4.9.3, 4.9.4, 5.1.0, 5.2.0, 5.3.0, 5.4.0 ]</msg></result>
<result><category>dev-lang</category><package>ghc</package><version>7.8.3</version><class>MissingSlotDep</class><msg>'&gt;=sys-devel/binutils-2.17' matches more than one slot: [ 2.21.1, 2.22, 2.23.2, 2.24, 2.25, 2.25.1, 2.26.1, git ]</msg></result>
<result><category>dev-lang</category><package>ghc</package><version>7.8.3</version><class>MissingSlotDep</class><msg>'&gt;=sys-devel/gcc-2.95.3' matches more than one slot: [ 2.95.3, 3.3.6, 3.4.6, 4.0.4, 4.1.2, 4.2.4, 4.3.6, 4.4.7, 4.5.4, 4.6.4, 4.7.4, 4.8.5, 4.9.3, 4.9.4, 5.1.0, 5.2.0, 5.3.0, 5.4.0 ]</msg></result>
<result><category>dev-lang</category><package>ghc</package><version>7.8.4</version><class>MissingSlotDep</class><msg>'&gt;=sys-devel/binutils-2.17' matches more than one slot: [ 2.21.1, 2.22, 2.23.2, 2.24, 2.25, 2.25.1, 2.26.1, git ]</msg></result>
<result><category>dev-lang</category><package>ghc</package><version>7.8.4</version><class>MissingSlotDep</class><msg>'&gt;=sys-devel/gcc-2.95.3' matches more than one slot: [ 2.95.3, 3.3.6, 3.4.6, 4.0.4, 4.1.2, 4.2.4, 4.3.6, 4.4.7, 4.5.4, 4.6.4, 4.7.4, 4.8.5, 4.9.3, 4.9.4, 5.1.0, 5.2.0, 5.3.0, 5.4.0 ]</msg></result>
<result><category>dev-lang</category><package>ghc</package><version>7.10.2</version><class>DroppedKeyword</class><msg>keywords dropped: alpha, ia64, ppc, ppc64, sparc</msg></result>
<result><category>dev-lang</category><package>gnat-gcc</package><version>4.9.3</version><class>DroppedKeyword</class><msg>keywords dropped: sparc</msg></result>
<result><category>dev-lang</category><package>gnat-gcc</package><version>4.4.7</version><class>DroppedKeyword</class><msg>keywords dropped: ppc</msg></result>
<result><category>dev-lang</category><package>helium</package><version>1.8.1</version><class>DroppedKeyword</class><msg>keywords dropped: ppc</msg></result>
<result><category>dev-lang</category><package>inform</package><class>PkgMetadataXmlInvalidProjectError</class><msg>dev-lang/inform metadata.xml &lt;maintainer/&gt; references invalid project 'games@gentoo.org'</msg></result>
<result><category>dev-lang</category><package>lazarus</package><version>1.6.0-r1</version><class>DroppedKeyword</class><msg>keywords dropped: ppc</msg></result>
<result><category>dev-lang</category><package>lua</package><version>5.1.5-r2</version><class>MissingSlotDep</class><msg>'sys-libs/readline' matches more than one slot: [ 0, 4, 5 ]</msg></result>
<result><category>dev-lang</category><package>lua</package><version>5.2.3</version><class>MissingSlotDep</class><msg>'sys-libs/readline' matches more than one slot: [ 0, 4, 5 ]</msg></result>
<result><category>dev-lang</category><package>lua</package><version>5.2.3-r1</version><class>MissingSlotDep</class><msg>'sys-libs/readline' matches more than one slot: [ 0, 4, 5 ]</msg></result>
<result><category>dev-lang</category><package>lua</package><version>5.1.5-r100</version><class>DroppedKeyword</class><msg>keywords dropped: arm64</msg></result>
<result><category>dev-lang</category><package>maude</package><version>2.6-r1</version><class>MissingSlotDep</class><msg>'&gt;=dev-libs/gmp-4.1.3' matches more than one slot: [ 0, 3 ]</msg></result>
<result><category>dev-lang</category><package>mlton</package><version>20130715</version><class>MissingSlotDep</class><msg>'dev-libs/gmp' matches more than one slot: [ 0, 3 ]</msg></result>
<result><category>dev-lang</category><package>nqp</package><version>2016.03</version><class>MissingSlotDep</class><msg>'&gt;=virtual/jre-1.7' matches more than one slot: [ 1.7, 1.8 ]</msg></result>
<result><category>dev-lang</category><package>nqp</package><version>2016.04</version><class>MissingSlotDep</class><msg>'&gt;=virtual/jre-1.7' matches more than one slot: [ 1.7, 1.8 ]</msg></result>
<result><category>dev-lang</category><package>ocaml</package><version>4.02.3</version><class>MissingSlotDep</class><msg>'sys-libs/ncurses' matches more than one slot: [ 0, 5 ]</msg></result>
<result><category>dev-lang</category><package>parrot</package><version>7.1.0</version><class>MissingSlotDep</class><msg>'dev-libs/openssl' matches more than one slot: [ 0, 0.9.8 ]</msg></result>
<result><category>dev-lang</category><package>parrot</package><version>7.1.0</version><class>MissingSlotDep</class><msg>'sys-libs/readline' matches more than one slot: [ 0, 4, 5 ]</msg></result>
<result><category>dev-lang</category><package>parrot</package><version>7.1.0</version><class>MissingSlotDep</class><msg>'&gt;=dev-libs/gmp-4.1.4' matches more than one slot: [ 0, 3 ]</msg></result>
<result><category>dev-lang</category><package>parrot</package><version>7.5.0</version><class>MissingSlotDep</class><msg>'dev-libs/openssl' matches more than one slot: [ 0, 0.9.8 ]</msg></result>
<result><category>dev-lang</category><package>parrot</package><version>7.5.0</version><class>MissingSlotDep</class><msg>'sys-libs/readline' matches more than one slot: [ 0, 4, 5 ]</msg></result>
<result><category>dev-lang</category><package>parrot</package><version>7.5.0</version><class>MissingSlotDep</class><msg>'&gt;=dev-libs/gmp-4.1.4' matches more than one slot: [ 0, 3 ]</msg></result>
<result><category>dev-lang</category><package>parrot</package><version>7.11.0</version><class>MissingSlotDep</class><msg>'dev-libs/openssl' matches more than one slot: [ 0, 0.9.8 ]</msg></result>
<result><category>dev-lang</category><package>parrot</package><version>7.11.0</version><class>MissingSlotDep</class><msg>'sys-libs/readline' matches more than one slot: [ 0, 4, 5 ]</msg></result>
<result><category>dev-lang</category><package>parrot</package><version>7.11.0</version><class>MissingSlotDep</class><msg>'&gt;=dev-libs/gmp-4.1.4' matches more than one slot: [ 0, 3 ]</msg></result>
<result><category>dev-lang</category><package>parrot</package><version>8.1.0</version><class>MissingSlotDep</class><msg>'dev-libs/openssl' matches more than one slot: [ 0, 0.9.8 ]</msg></result>
<result><category>dev-lang</category><package>parrot</package><version>8.1.0</version><class>MissingSlotDep</class><msg>'sys-libs/readline' matches more than one slot: [ 0, 4, 5 ]</msg></result>
<result><category>dev-lang</category><package>parrot</package><version>8.1.0</version><class>MissingSlotDep</class><msg>'&gt;=dev-libs/gmp-4.1.4' matches more than one slot: [ 0, 3 ]</msg></result>
<result><category>dev-lang</category><package>php</package><version>5.5.37</version><class>MissingSlotDep</class><msg>'&gt;=dev-libs/openssl-0.9.7' matches more than one slot: [ 0, 0.9.8 ]</msg></result>
<result><category>dev-lang</category><package>php</package><version>5.5.37</version><class>MissingSlotDep</class><msg>'dev-db/postgresql' matches more than one slot: [ 9.0, 9.1, 9.2, 9.3, 9.4, 9.5, 9.6, 9.7 ]</msg></result>
<result><category>dev-lang</category><package>php</package><version>5.5.37</version><class>MissingSlotDep</class><msg>'sys-libs/readline' matches more than one slot: [ 0, 4, 5 ]</msg></result>
<result><category>dev-lang</category><package>php</package><version>5.5.37</version><class>MissingSlotDep</class><msg>'=sys-libs/db-4*' matches more than one slot: [ 4.2, 4.3, 4.4, 4.5, 4.6, 4.7, 4.8 ]</msg></result>
<result><category>dev-lang</category><package>php</package><version>5.5.37</version><class>MissingSlotDep</class><msg>'&gt;=dev-libs/gmp-4.1.2' matches more than one slot: [ 0, 3 ]</msg></result>
<result><category>dev-lang</category><package>php</package><version>5.5.38</version><class>MissingSlotDep</class><msg>'&gt;=dev-libs/openssl-0.9.7' matches more than one slot: [ 0, 0.9.8 ]</msg></result>
<result><category>dev-lang</category><package>php</package><version>5.5.38</version><class>MissingSlotDep</class><msg>'dev-db/postgresql' matches more than one slot: [ 9.0, 9.1, 9.2, 9.3, 9.4, 9.5, 9.6, 9.7 ]</msg></result>
<result><category>dev-lang</category><package>php</package><version>5.5.38</version><class>MissingSlotDep</class><msg>'sys-libs/readline' matches more than one slot: [ 0, 4, 5 ]</msg></result>
<result><category>dev-lang</category><package>php</package><version>5.5.38</version><class>MissingSlotDep</class><msg>'=sys-libs/db-4*' matches more than one slot: [ 4.2, 4.3, 4.4, 4.5, 4.6, 4.7, 4.8 ]</msg></result>
<result><category>dev-lang</category><package>php</package><version>5.5.38</version><class>MissingSlotDep</class><msg>'&gt;=dev-libs/gmp-4.1.2' matches more than one slot: [ 0, 3 ]</msg></result>
<result><category>dev-lang</category><package>python</package><version>2.7.10-r1</version><class>NonExistentDeps</class><msg>depset depends: nonexistent deps: [ sys-libs/db:5.2, sys-libs/db:5.0 ]</msg></result>
<result><category>dev-lang</category><package>python</package><version>2.7.10-r1</version><class>NonExistentDeps</class><msg>depset rdepends: nonexistent deps: [ sys-libs/db:5.2, sys-libs/db:5.0 ]</msg></result>
<result><category>dev-lang</category><package>python</package><version>2.7.11-r2</version><class>NonExistentDeps</class><msg>depset depends: nonexistent deps: [ sys-libs/db:5.2, sys-libs/db:5.0 ]</msg></result>
<result><category>dev-lang</category><package>python</package><version>2.7.11-r2</version><class>NonExistentDeps</class><msg>depset rdepends: nonexistent deps: [ sys-libs/db:5.2, sys-libs/db:5.0 ]</msg></result>
<result><category>dev-lang</category><package>python</package><version>2.7.12</version><class>NonExistentDeps</class><msg>depset depends: nonexistent deps: [ sys-libs/db:5.2, sys-libs/db:5.0 ]</msg></result>
<result><category>dev-lang</category><package>python</package><version>2.7.12</version><class>NonExistentDeps</class><msg>depset rdepends: nonexistent deps: [ sys-libs/db:5.2, sys-libs/db:5.0 ]</msg></result>
<result><category>dev-lang</category><package>rubinius</package><version>3.43</version><class>MissingSlotDep</class><msg>'sys-libs/ncurses' matches more than one slot: [ 0, 5 ]</msg></result>
<result><category>dev-lang</category><package>rust</package><version>1.9.0</version><class>BadInsIntoDir</class><msg>ebuild uses insinto /etc/env.d on line 134</msg></result>
<result><category>dev-lang</category><package>rust</package><version>1.10.0</version><class>BadInsIntoDir</class><msg>ebuild uses insinto /etc/env.d on line 129</msg></result>
<result><category>dev-lang</category><package>rust</package><version>1.11.0</version><class>BadInsIntoDir</class><msg>ebuild uses insinto /etc/env.d on line 129</msg></result>
<result><category>dev-lang</category><package>rust-bin</package><version>1.2.0</version><class>BadInsIntoDir</class><msg>ebuild uses insinto /etc/env.d on line 68</msg></result>
<result><category>dev-lang</category><package>rust-bin</package><version>1.3.0</version><class>BadInsIntoDir</class><msg>ebuild uses insinto /etc/env.d on line 68</msg></result>
<result><category>dev-lang</category><package>rust-bin</package><version>1.5.0</version><class>BadInsIntoDir</class><msg>ebuild uses insinto /etc/env.d on line 77</msg></result>
<result><category>dev-lang</category><package>rust-bin</package><version>1.6.0</version><class>BadInsIntoDir</class><msg>ebuild uses insinto /etc/env.d on line 77</msg></result>
<result><category>dev-lang</category><package>rust-bin</package><version>1.7.0</version><class>BadInsIntoDir</class><msg>ebuild uses insinto /etc/env.d on line 77</msg></result>
<result><category>dev-lang</category><package>rust-bin</package><version>1.8.0</version><class>BadInsIntoDir</class><msg>ebuild uses insinto /etc/env.d on line 77</msg></result>
<result><category>dev-lang</category><package>scala</package><version>2.11.4-r1</version><class>NonExistentDeps</class><msg>depset depends: nonexistent dep: [ =virtual/jdk-1.6* ]</msg></result>
<result><category>dev-lang</category><package>spidermonkey</package><version>17.0.0-r4</version><class>DroppedKeyword</class><msg>keywords dropped: arm64</msg></result>
<result><category>dev-lang</category><package>teyjus</package><version>2.0.2</version><class>MissingSlotDep</class><msg>'&gt;=sys-devel/binutils-2.17' matches more than one slot: [ 2.21.1, 2.22, 2.23.2, 2.24, 2.25, 2.25.1, 2.26.1, git ]</msg></result>
<result><category>dev-lang</category><package>teyjus</package><version>2.0.2</version><class>MissingSlotDep</class><msg>'&gt;=sys-devel/gcc-2.95.3' matches more than one slot: [ 2.95.3, 3.3.6, 3.4.6, 4.0.4, 4.1.2, 4.2.4, 4.3.6, 4.4.7, 4.5.4, 4.6.4, 4.7.4, 4.8.5, 4.9.3, 4.9.4, 5.1.0, 5.2.0, 5.3.0, 5.4.0 ]</msg></result>
<result><category>dev-lang</category><package>vala</package><class>PkgMetadataXmlInvalidProjectError</class><msg>dev-lang/vala metadata.xml &lt;maintainer/&gt; references invalid project 'gnome@gentoo.org'</msg></result>
<result><category>kde-frameworks</category><package>attica</package><class>PkgMetadataXmlInvalidProjectError</class><msg>kde-frameworks/attica metadata.xml &lt;maintainer/&gt; references invalid project 'kde@gentoo.org'</msg></result>
<result><category>kde-frameworks</category><package>baloo</package><class>PkgMetadataXmlInvalidProjectError</class><msg>kde-frameworks/baloo metadata.xml &lt;maintainer/&gt; references invalid project 'kde@gentoo.org'</msg></result>
<result><category>kde-frameworks</category><package>bluez-qt</package><class>PkgMetadataXmlInvalidProjectError</class><msg>kde-frameworks/bluez-qt metadata.xml &lt;maintainer/&gt; references invalid project 'kde@gentoo.org'</msg></result>
<result><category>kde-frameworks</category><package>breeze-icons</package><class>PkgMetadataXmlInvalidProjectError</class><msg>kde-frameworks/breeze-icons metadata.xml &lt;maintainer/&gt; references invalid project 'kde@gentoo.org'</msg></result>
<result><category>kde-frameworks</category><package>extra-cmake-modules</package><class>PkgMetadataXmlInvalidProjectError</class><msg>kde-frameworks/extra-cmake-modules metadata.xml &lt;maintainer/&gt; references invalid project 'kde@gentoo.org'</msg></result>
<result><category>kde-frameworks</category><package>frameworkintegration</package><class>PkgMetadataXmlInvalidProjectError</class><msg>kde-frameworks/frameworkintegration metadata.xml &lt;maintainer/&gt; references invalid project 'kde@gentoo.org'</msg></result>
<result><category>kde-frameworks</category><package>kactivities</package><class>PkgMetadataXmlInvalidProjectError</class><msg>kde-frameworks/kactivities metadata.xml &lt;maintainer/&gt; references invalid project 'kde@gentoo.org'</msg></result>
<result><category>kde-frameworks</category><package>kactivities-stats</package><class>PkgMetadataXmlInvalidProjectError</class><msg>kde-frameworks/kactivities-stats metadata.xml &lt;maintainer/&gt; references invalid project 'kde@gentoo.org'</msg></result>
<result><category>kde-frameworks</category><package>kapidox</package><class>PkgMetadataXmlInvalidProjectError</class><msg>kde-frameworks/kapidox metadata.xml &lt;maintainer/&gt; references invalid project 'kde@gentoo.org'</msg></result>
<result><category>kde-frameworks</category><package>karchive</package><class>PkgMetadataXmlInvalidProjectError</class><msg>kde-frameworks/karchive metadata.xml &lt;maintainer/&gt; references invalid project 'kde@gentoo.org'</msg></result>
<result><category>kde-frameworks</category><package>kauth</package><class>PkgMetadataXmlInvalidProjectError</class><msg>kde-frameworks/kauth metadata.xml &lt;maintainer/&gt; references invalid project 'kde@gentoo.org'</msg></result>
<result><category>kde-frameworks</category><package>kbookmarks</package><class>PkgMetadataXmlInvalidProjectError</class><msg>kde-frameworks/kbookmarks metadata.xml &lt;maintainer/&gt; references invalid project 'kde@gentoo.org'</msg></result>
<result><category>kde-frameworks</category><package>kcmutils</package><class>PkgMetadataXmlInvalidProjectError</class><msg>kde-frameworks/kcmutils metadata.xml &lt;maintainer/&gt; references invalid project 'kde@gentoo.org'</msg></result>
<result><category>kde-frameworks</category><package>kcodecs</package><class>PkgMetadataXmlInvalidProjectError</class><msg>kde-frameworks/kcodecs metadata.xml &lt;maintainer/&gt; references invalid project 'kde@gentoo.org'</msg></result>
<result><category>kde-frameworks</category><package>kcompletion</package><class>PkgMetadataXmlInvalidProjectError</class><msg>kde-frameworks/kcompletion metadata.xml &lt;maintainer/&gt; references invalid project 'kde@gentoo.org'</msg></result>
<result><category>kde-frameworks</category><package>kconfig</package><class>PkgMetadataXmlInvalidProjectError</class><msg>kde-frameworks/kconfig metadata.xml &lt;maintainer/&gt; references invalid project 'kde@gentoo.org'</msg></result>
<result><category>kde-frameworks</category><package>kconfigwidgets</package><class>PkgMetadataXmlInvalidProjectError</class><msg>kde-frameworks/kconfigwidgets metadata.xml &lt;maintainer/&gt; references invalid project 'kde@gentoo.org'</msg></result>
<result><category>kde-frameworks</category><package>kcoreaddons</package><class>PkgMetadataXmlInvalidProjectError</class><msg>kde-frameworks/kcoreaddons metadata.xml &lt;maintainer/&gt; references invalid project 'kde@gentoo.org'</msg></result>
<result><category>kde-frameworks</category><package>kcrash</package><class>PkgMetadataXmlInvalidProjectError</class><msg>kde-frameworks/kcrash metadata.xml &lt;maintainer/&gt; references invalid project 'kde@gentoo.org'</msg></result>
<result><category>kde-frameworks</category><package>kdbusaddons</package><class>PkgMetadataXmlInvalidProjectError</class><msg>kde-frameworks/kdbusaddons metadata.xml &lt;maintainer/&gt; references invalid project 'kde@gentoo.org'</msg></result>
<result><category>kde-frameworks</category><package>kdeclarative</package><class>PkgMetadataXmlInvalidProjectError</class><msg>kde-frameworks/kdeclarative metadata.xml &lt;maintainer/&gt; references invalid project 'kde@gentoo.org'</msg></result>
<result><category>kde-frameworks</category><package>kded</package><class>PkgMetadataXmlInvalidProjectError</class><msg>kde-frameworks/kded metadata.xml &lt;maintainer/&gt; references invalid project 'kde@gentoo.org'</msg></result>
<result><category>kde-frameworks</category><package>kdelibs4support</package><class>PkgMetadataXmlInvalidProjectError</class><msg>kde-frameworks/kdelibs4support metadata.xml &lt;maintainer/&gt; references invalid project 'kde@gentoo.org'</msg></result>
<result><category>kde-frameworks</category><package>kdesignerplugin</package><class>PkgMetadataXmlInvalidProjectError</class><msg>kde-frameworks/kdesignerplugin metadata.xml &lt;maintainer/&gt; references invalid project 'kde@gentoo.org'</msg></result>
<result><category>kde-frameworks</category><package>kdesu</package><class>PkgMetadataXmlInvalidProjectError</class><msg>kde-frameworks/kdesu metadata.xml &lt;maintainer/&gt; references invalid project 'kde@gentoo.org'</msg></result>
<result><category>kde-frameworks</category><package>kdewebkit</package><class>PkgMetadataXmlInvalidProjectError</class><msg>kde-frameworks/kdewebkit metadata.xml &lt;maintainer/&gt; references invalid project 'kde@gentoo.org'</msg></result>
<result><category>kde-frameworks</category><package>kdnssd</package><class>PkgMetadataXmlInvalidProjectError</class><msg>kde-frameworks/kdnssd metadata.xml &lt;maintainer/&gt; references invalid project 'kde@gentoo.org'</msg></result>
<result><category>kde-frameworks</category><package>kdoctools</package><class>PkgMetadataXmlInvalidProjectError</class><msg>kde-frameworks/kdoctools metadata.xml &lt;maintainer/&gt; references invalid project 'kde@gentoo.org'</msg></result>
<result><category>kde-frameworks</category><package>kemoticons</package><class>PkgMetadataXmlInvalidProjectError</class><msg>kde-frameworks/kemoticons metadata.xml &lt;maintainer/&gt; references invalid project 'kde@gentoo.org'</msg></result>
<result><category>kde-frameworks</category><package>kf-env</package><class>PkgMetadataXmlInvalidProjectError</class><msg>kde-frameworks/kf-env metadata.xml &lt;maintainer/&gt; references invalid project 'kde@gentoo.org'</msg></result>
<result><category>kde-frameworks</category><package>kfilemetadata</package><class>PkgMetadataXmlInvalidProjectError</class><msg>kde-frameworks/kfilemetadata metadata.xml &lt;maintainer/&gt; references invalid project 'kde@gentoo.org'</msg></result>
<result><category>kde-frameworks</category><package>kglobalaccel</package><class>PkgMetadataXmlInvalidProjectError</class><msg>kde-frameworks/kglobalaccel metadata.xml &lt;maintainer/&gt; references invalid project 'kde@gentoo.org'</msg></result>
<result><category>kde-frameworks</category><package>kguiaddons</package><class>PkgMetadataXmlInvalidProjectError</class><msg>kde-frameworks/kguiaddons metadata.xml &lt;maintainer/&gt; references invalid project 'kde@gentoo.org'</msg></result>
<result><category>kde-frameworks</category><package>khtml</package><class>PkgMetadataXmlInvalidProjectError</class><msg>kde-frameworks/khtml metadata.xml &lt;maintainer/&gt; references invalid project 'kde@gentoo.org'</msg></result>
<result><category>kde-frameworks</category><package>ki18n</package><class>PkgMetadataXmlInvalidProjectError</class><msg>kde-frameworks/ki18n metadata.xml &lt;maintainer/&gt; references invalid project 'kde@gentoo.org'</msg></result>
<result><category>kde-frameworks</category><package>kiconthemes</package><class>PkgMetadataXmlInvalidProjectError</class><msg>kde-frameworks/kiconthemes metadata.xml &lt;maintainer/&gt; references invalid project 'kde@gentoo.org'</msg></result>
<result><category>kde-frameworks</category><package>kidletime</package><class>PkgMetadataXmlInvalidProjectError</class><msg>kde-frameworks/kidletime metadata.xml &lt;maintainer/&gt; references invalid project 'kde@gentoo.org'</msg></result>
<result><category>kde-frameworks</category><package>kimageformats</package><class>PkgMetadataXmlInvalidProjectError</class><msg>kde-frameworks/kimageformats metadata.xml &lt;maintainer/&gt; references invalid project 'kde@gentoo.org'</msg></result>
<result><category>kde-frameworks</category><package>kinit</package><class>PkgMetadataXmlInvalidProjectError</class><msg>kde-frameworks/kinit metadata.xml &lt;maintainer/&gt; references invalid project 'kde@gentoo.org'</msg></result>
<result><category>kde-frameworks</category><package>kio</package><class>PkgMetadataXmlInvalidProjectError</class><msg>kde-frameworks/kio metadata.xml &lt;maintainer/&gt; references invalid project 'kde@gentoo.org'</msg></result>
<result><category>kde-frameworks</category><package>kitemmodels</package><class>PkgMetadataXmlInvalidProjectError</class><msg>kde-frameworks/kitemmodels metadata.xml &lt;maintainer/&gt; references invalid project 'kde@gentoo.org'</msg></result>
<result><category>kde-frameworks</category><package>kitemviews</package><class>PkgMetadataXmlInvalidProjectError</class><msg>kde-frameworks/kitemviews metadata.xml &lt;maintainer/&gt; references invalid project 'kde@gentoo.org'</msg></result>
<result><category>kde-frameworks</category><package>kjobwidgets</package><class>PkgMetadataXmlInvalidProjectError</class><msg>kde-frameworks/kjobwidgets metadata.xml &lt;maintainer/&gt; references invalid project 'kde@gentoo.org'</msg></result>
<result><category>kde-frameworks</category><package>kjs</package><class>PkgMetadataXmlInvalidProjectError</class><msg>kde-frameworks/kjs metadata.xml &lt;maintainer/&gt; references invalid project 'kde@gentoo.org'</msg></result>
<result><category>kde-frameworks</category><package>kjsembed</package><class>PkgMetadataXmlInvalidProjectError</class><msg>kde-frameworks/kjsembed metadata.xml &lt;maintainer/&gt; references invalid project 'kde@gentoo.org'</msg></result>
<result><category>kde-frameworks</category><package>kmediaplayer</package><class>PkgMetadataXmlInvalidProjectError</class><msg>kde-frameworks/kmediaplayer metadata.xml &lt;maintainer/&gt; references invalid project 'kde@gentoo.org'</msg></result>
<result><category>kde-frameworks</category><package>knewstuff</package><class>PkgMetadataXmlInvalidProjectError</class><msg>kde-frameworks/knewstuff metadata.xml &lt;maintainer/&gt; references invalid project 'kde@gentoo.org'</msg></result>
<result><category>kde-frameworks</category><package>knotifications</package><class>PkgMetadataXmlInvalidProjectError</class><msg>kde-frameworks/knotifications metadata.xml &lt;maintainer/&gt; references invalid project 'kde@gentoo.org'</msg></result>
<result><category>kde-frameworks</category><package>knotifications</package><version>5.23.0</version><class>NonExistentDeps</class><msg>depset depends: nonexistent dep: [ &gt;=dev-qt/qtspeech-5.6.1:5 ]</msg></result>
<result><category>kde-frameworks</category><package>knotifications</package><version>5.23.0</version><class>NonExistentDeps</class><msg>depset rdepends: nonexistent dep: [ &gt;=dev-qt/qtspeech-5.6.1:5 ]</msg></result>
<result><category>kde-frameworks</category><package>knotifications</package><version>5.25.0</version><class>NonExistentDeps</class><msg>depset depends: nonexistent dep: [ &gt;=dev-qt/qtspeech-5.6.1:5 ]</msg></result>
<result><category>kde-frameworks</category><package>knotifications</package><version>5.25.0</version><class>NonExistentDeps</class><msg>depset rdepends: nonexistent dep: [ &gt;=dev-qt/qtspeech-5.6.1:5 ]</msg></result>
<result><category>kde-frameworks</category><package>knotifyconfig</package><class>PkgMetadataXmlInvalidProjectError</class><msg>kde-frameworks/knotifyconfig metadata.xml &lt;maintainer/&gt; references invalid project 'kde@gentoo.org'</msg></result>
<result><category>kde-frameworks</category><package>kpackage</package><class>PkgMetadataXmlInvalidProjectError</class><msg>kde-frameworks/kpackage metadata.xml &lt;maintainer/&gt; references invalid project 'kde@gentoo.org'</msg></result>
<result><category>kde-frameworks</category><package>kparts</package><class>PkgMetadataXmlInvalidProjectError</class><msg>kde-frameworks/kparts metadata.xml &lt;maintainer/&gt; references invalid project 'kde@gentoo.org'</msg></result>
<result><category>kde-frameworks</category><package>kpeople</package><class>PkgMetadataXmlInvalidProjectError</class><msg>kde-frameworks/kpeople metadata.xml &lt;maintainer/&gt; references invalid project 'kde@gentoo.org'</msg></result>
<result><category>kde-frameworks</category><package>kplotting</package><class>PkgMetadataXmlInvalidProjectError</class><msg>kde-frameworks/kplotting metadata.xml &lt;maintainer/&gt; references invalid project 'kde@gentoo.org'</msg></result>
<result><category>kde-frameworks</category><package>kpty</package><class>PkgMetadataXmlInvalidProjectError</class><msg>kde-frameworks/kpty metadata.xml &lt;maintainer/&gt; references invalid project 'kde@gentoo.org'</msg></result>
<result><category>kde-frameworks</category><package>kross</package><class>PkgMetadataXmlInvalidProjectError</class><msg>kde-frameworks/kross metadata.xml &lt;maintainer/&gt; references invalid project 'kde@gentoo.org'</msg></result>
<result><category>kde-frameworks</category><package>krunner</package><class>PkgMetadataXmlInvalidProjectError</class><msg>kde-frameworks/krunner metadata.xml &lt;maintainer/&gt; references invalid project 'kde@gentoo.org'</msg></result>
<result><category>kde-frameworks</category><package>kservice</package><class>PkgMetadataXmlInvalidProjectError</class><msg>kde-frameworks/kservice metadata.xml &lt;maintainer/&gt; references invalid project 'kde@gentoo.org'</msg></result>
<result><category>kde-frameworks</category><package>ktexteditor</package><class>PkgMetadataXmlInvalidProjectError</class><msg>kde-frameworks/ktexteditor metadata.xml &lt;maintainer/&gt; references invalid project 'kde@gentoo.org'</msg></result>
<result><category>kde-frameworks</category><package>ktextwidgets</package><class>PkgMetadataXmlInvalidProjectError</class><msg>kde-frameworks/ktextwidgets metadata.xml &lt;maintainer/&gt; references invalid project 'kde@gentoo.org'</msg></result>
<result><category>kde-frameworks</category><package>ktextwidgets</package><version>5.23.0</version><class>NonExistentDeps</class><msg>depset depends: nonexistent dep: [ &gt;=dev-qt/qtspeech-5.6.1:5 ]</msg></result>
<result><category>kde-frameworks</category><package>ktextwidgets</package><version>5.23.0</version><class>NonExistentDeps</class><msg>depset rdepends: nonexistent dep: [ &gt;=dev-qt/qtspeech-5.6.1:5 ]</msg></result>
<result><category>kde-frameworks</category><package>ktextwidgets</package><version>5.25.0</version><class>NonExistentDeps</class><msg>depset depends: nonexistent dep: [ &gt;=dev-qt/qtspeech-5.6.1:5 ]</msg></result>
<result><category>kde-frameworks</category><package>ktextwidgets</package><version>5.25.0</version><class>NonExistentDeps</class><msg>depset rdepends: nonexistent dep: [ &gt;=dev-qt/qtspeech-5.6.1:5 ]</msg></result>
<result><category>kde-frameworks</category><package>kunitconversion</package><class>PkgMetadataXmlInvalidProjectError</class><msg>kde-frameworks/kunitconversion metadata.xml &lt;maintainer/&gt; references invalid project 'kde@gentoo.org'</msg></result>
<result><category>kde-frameworks</category><package>kwallet</package><class>PkgMetadataXmlInvalidProjectError</class><msg>kde-frameworks/kwallet metadata.xml &lt;maintainer/&gt; references invalid project 'kde@gentoo.org'</msg></result>
<result><category>kde-frameworks</category><package>kwayland</package><class>PkgMetadataXmlInvalidProjectError</class><msg>kde-frameworks/kwayland metadata.xml &lt;maintainer/&gt; references invalid project 'kde@gentoo.org'</msg></result>
<result><category>kde-frameworks</category><package>kwidgetsaddons</package><class>PkgMetadataXmlInvalidProjectError</class><msg>kde-frameworks/kwidgetsaddons metadata.xml &lt;maintainer/&gt; references invalid project 'kde@gentoo.org'</msg></result>
<result><category>kde-frameworks</category><package>kwindowsystem</package><class>PkgMetadataXmlInvalidProjectError</class><msg>kde-frameworks/kwindowsystem metadata.xml &lt;maintainer/&gt; references invalid project 'kde@gentoo.org'</msg></result>
<result><category>kde-frameworks</category><package>kxmlgui</package><class>PkgMetadataXmlInvalidProjectError</class><msg>kde-frameworks/kxmlgui metadata.xml &lt;maintainer/&gt; references invalid project 'kde@gentoo.org'</msg></result>
<result><category>kde-frameworks</category><package>kxmlrpcclient</package><class>PkgMetadataXmlInvalidProjectError</class><msg>kde-frameworks/kxmlrpcclient metadata.xml &lt;maintainer/&gt; references invalid project 'kde@gentoo.org'</msg></result>
<result><category>kde-frameworks</category><package>modemmanager-qt</package><class>PkgMetadataXmlInvalidProjectError</class><msg>kde-frameworks/modemmanager-qt metadata.xml &lt;maintainer/&gt; references invalid project 'kde@gentoo.org'</msg></result>
<result><category>kde-frameworks</category><package>networkmanager-qt</package><class>PkgMetadataXmlInvalidProjectError</class><msg>kde-frameworks/networkmanager-qt metadata.xml &lt;maintainer/&gt; references invalid project 'kde@gentoo.org'</msg></result>
<result><category>kde-frameworks</category><package>oxygen-icons</package><class>PkgMetadataXmlInvalidProjectError</class><msg>kde-frameworks/oxygen-icons metadata.xml &lt;maintainer/&gt; references invalid project 'kde@gentoo.org'</msg></result>
<result><category>kde-frameworks</category><package>oxygen-icons</package><version>5.23.0</version><class>DroppedKeyword</class><msg>keywords dropped: arm64, ppc, ppc64</msg></result>
<result><category>kde-frameworks</category><package>plasma</package><class>PkgMetadataXmlInvalidProjectError</class><msg>kde-frameworks/plasma metadata.xml &lt;maintainer/&gt; references invalid project 'kde@gentoo.org'</msg></result>
<result><category>kde-frameworks</category><package>solid</package><class>PkgMetadataXmlInvalidProjectError</class><msg>kde-frameworks/solid metadata.xml &lt;maintainer/&gt; references invalid project 'kde@gentoo.org'</msg></result>
<result><category>kde-frameworks</category><package>sonnet</package><class>PkgMetadataXmlInvalidProjectError</class><msg>kde-frameworks/sonnet metadata.xml &lt;maintainer/&gt; references invalid project 'kde@gentoo.org'</msg></result>
<result><category>kde-frameworks</category><package>threadweaver</package><class>PkgMetadataXmlInvalidProjectError</class><msg>kde-frameworks/threadweaver metadata.xml &lt;maintainer/&gt; references invalid project 'kde@gentoo.org'</msg></result>
<result><category>net-mail</category><package>courier-imap</package><version>4.16.0-r1</version><class>DroppedKeyword</class><msg>keywords dropped: alpha, arm, ia64, mips, ppc, s390, sh, sparc</msg></result>
<result><category>net-mail</category><package>cyrus-imap-admin</package><version>2.4.17-r1</version><class>MissingSlotDep</class><msg>'&gt;=dev-libs/openssl-0.9.6' matches more than one slot: [ 0, 0.9.8 ]</msg></result>
<result><category>net-mail</category><package>cyrus-imap-admin</package><version>2.4.17-r1</version><class>MissingSlotDep</class><msg>'&gt;=sys-libs/db-3.2' matches more than one slot: [ 3, 4.2, 4.3, 4.4, 4.5, 4.6, 4.7, 4.8, 5.1, 5.3, 6.0, 6.1, 6.2 ]</msg></result>
<result><category>net-mail</category><package>dovecot</package><version>2.2.19-r1</version><class>DroppedKeyword</class><msg>keywords dropped: alpha, ia64, mips, sh, sparc</msg></result>
<result><category>net-mail</category><package>fetchmail</package><version>6.3.26-r2</version><class>MissingSlotDep</class><msg>'&gt;=dev-libs/openssl-0.9.6' matches more than one slot: [ 0, 0.9.8 ]</msg></result>
<result><category>net-mail</category><package>gnubiff</package><version>2.2.15-r2</version><class>MissingSlotDep</class><msg>'dev-libs/openssl' matches more than one slot: [ 0, 0.9.8 ]</msg></result>
<result><category>net-mail</category><package>isync</package><version>1.0.6</version><class>MissingSlotDep</class><msg>'&gt;=sys-libs/db-4.2' matches more than one slot: [ 4.2, 4.3, 4.4, 4.5, 4.6, 4.7, 4.8, 5.1, 5.3, 6.0, 6.1, 6.2 ]</msg></result>
<result><category>net-mail</category><package>isync</package><version>1.0.6</version><class>MissingSlotDep</class><msg>'&gt;=dev-libs/openssl-0.9.6' matches more than one slot: [ 0, 0.9.8 ]</msg></result>
<result><category>net-mail</category><package>pfqueue</package><version>0.5.6</version><class>MissingSlotDep</class><msg>'sys-libs/ncurses' matches more than one slot: [ 0, 5 ]</msg></result>
<result><category>net-mail</category><package>qmailadmin</package><version>1.2.16</version><class>DroppedKeyword</class><msg>keywords dropped: ia64</msg></result>
<result><category>net-mail</category><package>spamcup</package><version>1.09</version><class>NonExistentDeps</class><msg>depset depends: nonexistent dep: [ &lt;dev-perl/libwww-perl-6 ]</msg></result>
<result><category>net-mail</category><package>spamcup</package><version>1.09</version><class>NonExistentDeps</class><msg>depset rdepends: nonexistent dep: [ &lt;dev-perl/libwww-perl-6 ]</msg></result>
<result><category>net-mail</category><package>up-imapproxy</package><version>1.2.7</version><class>MissingSlotDep</class><msg>'sys-libs/ncurses' matches more than one slot: [ 0, 5 ]</msg></result>
<result><category>net-mail</category><package>up-imapproxy</package><version>1.2.7</version><class>MissingSlotDep</class><msg>'dev-libs/openssl' matches more than one slot: [ 0, 0.9.8 ]</msg></result>
<result><category>games-fps</category><package>aaquake2</package><class>PkgMetadataXmlInvalidProjectError</class><msg>games-fps/aaquake2 metadata.xml &lt;maintainer/&gt; references invalid project 'games@gentoo.org'</msg></result>
<result><category>games-fps</category><package>aaut</package><class>PkgMetadataXmlInvalidProjectError</class><msg>games-fps/aaut metadata.xml &lt;maintainer/&gt; references invalid project 'games@gentoo.org'</msg></result>
<result><category>games-fps</category><package>alephone</package><class>PkgMetadataXmlInvalidProjectError</class><msg>games-fps/alephone metadata.xml &lt;maintainer/&gt; references invalid project 'games@gentoo.org'</msg></result>
<result><category>games-fps</category><package>alephone-infinity</package><class>PkgMetadataXmlInvalidProjectError</class><msg>games-fps/alephone-infinity metadata.xml &lt;maintainer/&gt; references invalid project 'games@gentoo.org'</msg></result>
<result><category>games-fps</category><package>alienarena</package><class>PkgMetadataXmlInvalidProjectError</class><msg>games-fps/alienarena metadata.xml &lt;maintainer/&gt; references invalid project 'games@gentoo.org'</msg></result>
<result><category>games-fps</category><package>avp</package><class>PkgMetadataXmlInvalidProjectError</class><msg>games-fps/avp metadata.xml &lt;maintainer/&gt; references invalid project 'games@gentoo.org'</msg></result>
<result><category>games-fps</category><package>blackshades</package><class>PkgMetadataXmlInvalidProjectError</class><msg>games-fps/blackshades metadata.xml &lt;maintainer/&gt; references invalid project 'games@gentoo.org'</msg></result>
<result><category>games-fps</category><package>darkplaces</package><class>PkgMetadataXmlInvalidProjectError</class><msg>games-fps/darkplaces metadata.xml &lt;maintainer/&gt; references invalid project 'games@gentoo.org'</msg></result>
<result><category>games-fps</category><package>doom-data</package><class>PkgMetadataXmlInvalidProjectError</class><msg>games-fps/doom-data metadata.xml &lt;maintainer/&gt; references invalid project 'games@gentoo.org'</msg></result>
<result><category>games-fps</category><package>doom3</package><class>PkgMetadataXmlInvalidProjectError</class><msg>games-fps/doom3 metadata.xml &lt;maintainer/&gt; references invalid project 'games@gentoo.org'</msg></result>
<result><category>games-fps</category><package>doom3-cdoom</package><class>PkgMetadataXmlInvalidProjectError</class><msg>games-fps/doom3-cdoom metadata.xml &lt;maintainer/&gt; references invalid project 'games@gentoo.org'</msg></result>
<result><category>games-fps</category><package>doom3-chextrek</package><class>PkgMetadataXmlInvalidProjectError</class><msg>games-fps/doom3-chextrek metadata.xml &lt;maintainer/&gt; references invalid project 'games@gentoo.org'</msg></result>
<result><category>games-fps</category><package>doom3-data</package><class>PkgMetadataXmlInvalidProjectError</class><msg>games-fps/doom3-data metadata.xml &lt;maintainer/&gt; references invalid project 'games@gentoo.org'</msg></result>
<result><category>games-fps</category><package>doom3-demo</package><class>PkgMetadataXmlInvalidProjectError</class><msg>games-fps/doom3-demo metadata.xml &lt;maintainer/&gt; references invalid project 'games@gentoo.org'</msg></result>
<result><category>games-fps</category><package>doom3-ducttape</package><class>PkgMetadataXmlInvalidProjectError</class><msg>games-fps/doom3-ducttape metadata.xml &lt;maintainer/&gt; references invalid project 'games@gentoo.org'</msg></result>
<result><category>games-fps</category><package>doom3-eventhorizon</package><class>PkgMetadataXmlInvalidProjectError</class><msg>games-fps/doom3-eventhorizon metadata.xml &lt;maintainer/&gt; references invalid project 'games@gentoo.org'</msg></result>
<result><category>games-fps</category><package>doom3-hellcampaign</package><class>PkgMetadataXmlInvalidProjectError</class><msg>games-fps/doom3-hellcampaign metadata.xml &lt;maintainer/&gt; references invalid project 'games@gentoo.org'</msg></result>
<result><category>games-fps</category><package>doom3-inhell</package><class>PkgMetadataXmlInvalidProjectError</class><msg>games-fps/doom3-inhell metadata.xml &lt;maintainer/&gt; references invalid project 'games@gentoo.org'</msg></result>
<result><category>games-fps</category><package>doom3-lms</package><class>PkgMetadataXmlInvalidProjectError</class><msg>games-fps/doom3-lms metadata.xml &lt;maintainer/&gt; references invalid project 'games@gentoo.org'</msg></result>
<result><category>games-fps</category><package>doom3-mitm</package><class>PkgMetadataXmlInvalidProjectError</class><msg>games-fps/doom3-mitm metadata.xml &lt;maintainer/&gt; references invalid project 'games@gentoo.org'</msg></result>
<result><category>games-fps</category><package>doom3-roe</package><class>PkgMetadataXmlInvalidProjectError</class><msg>games-fps/doom3-roe metadata.xml &lt;maintainer/&gt; references invalid project 'games@gentoo.org'</msg></result>
<result><category>games-fps</category><package>doomsday</package><class>PkgMetadataXmlInvalidProjectError</class><msg>games-fps/doomsday metadata.xml &lt;maintainer/&gt; references invalid project 'games@gentoo.org'</msg></result>
<result><category>games-fps</category><package>doomsday-resources</package><class>PkgMetadataXmlInvalidProjectError</class><msg>games-fps/doomsday-resources metadata.xml &lt;maintainer/&gt; references invalid project 'games@gentoo.org'</msg></result>
<result><category>games-fps</category><package>duke3d</package><class>PkgMetadataXmlInvalidProjectError</class><msg>games-fps/duke3d metadata.xml &lt;maintainer/&gt; references invalid project 'games@gentoo.org'</msg></result>
<result><category>games-fps</category><package>duke3d-data</package><class>PkgMetadataXmlInvalidProjectError</class><msg>games-fps/duke3d-data metadata.xml &lt;maintainer/&gt; references invalid project 'games@gentoo.org'</msg></result>
<result><category>games-fps</category><package>duke3d-data</package><version>1.0-r3</version><class>MissingUri</class><msg>file gog_duke_nukem_3d_atomic_edition_2.0.0.8.sh is unfetchable- no URI available, and RESTRICT=fetch isn't set</msg></result>
<result><category>games-fps</category><package>duke3d-demodata</package><class>PkgMetadataXmlInvalidProjectError</class><msg>games-fps/duke3d-demodata metadata.xml &lt;maintainer/&gt; references invalid project 'games@gentoo.org'</msg></result>
<result><category>games-fps</category><package>eduke32</package><class>PkgMetadataXmlInvalidProjectError</class><msg>games-fps/eduke32 metadata.xml &lt;maintainer/&gt; references invalid project 'games@gentoo.org'</msg></result>
<result><category>games-fps</category><package>enemy-territory</package><class>PkgMetadataXmlInvalidProjectError</class><msg>games-fps/enemy-territory metadata.xml &lt;maintainer/&gt; references invalid project 'games@gentoo.org'</msg></result>
<result><category>games-fps</category><package>enemy-territory-etpro</package><class>PkgMetadataXmlInvalidProjectError</class><msg>games-fps/enemy-territory-etpro metadata.xml &lt;maintainer/&gt; references invalid project 'games@gentoo.org'</msg></result>
<result><category>games-fps</category><package>enemy-territory-omnibot</package><class>PkgMetadataXmlInvalidProjectError</class><msg>games-fps/enemy-territory-omnibot metadata.xml &lt;maintainer/&gt; references invalid project 'games@gentoo.org'</msg></result>
<result><category>games-fps</category><package>enemy-territory-truecombat</package><class>PkgMetadataXmlInvalidProjectError</class><msg>games-fps/enemy-territory-truecombat metadata.xml &lt;maintainer/&gt; references invalid project 'games@gentoo.org'</msg></result>
<result><category>games-fps</category><package>etqw-bin</package><class>PkgMetadataXmlInvalidProjectError</class><msg>games-fps/etqw-bin metadata.xml &lt;maintainer/&gt; references invalid project 'games@gentoo.org'</msg></result>
<result><category>games-fps</category><package>etqw-data</package><class>PkgMetadataXmlInvalidProjectError</class><msg>games-fps/etqw-data metadata.xml &lt;maintainer/&gt; references invalid project 'games@gentoo.org'</msg></result>
<result><category>games-fps</category><package>etqw-demo</package><class>PkgMetadataXmlInvalidProjectError</class><msg>games-fps/etqw-demo metadata.xml &lt;maintainer/&gt; references invalid project 'games@gentoo.org'</msg></result>
<result><category>games-fps</category><package>ezquake-bin</package><class>PkgMetadataXmlInvalidProjectError</class><msg>games-fps/ezquake-bin metadata.xml &lt;maintainer/&gt; references invalid project 'games@gentoo.org'</msg></result>
<result><category>games-fps</category><package>freedoom</package><class>PkgMetadataXmlInvalidProjectError</class><msg>games-fps/freedoom metadata.xml &lt;maintainer/&gt; references invalid project 'games@gentoo.org'</msg></result>
<result><category>games-fps</category><package>glxquake-bin</package><class>PkgMetadataXmlInvalidProjectError</class><msg>games-fps/glxquake-bin metadata.xml &lt;maintainer/&gt; references invalid project 'games@gentoo.org'</msg></result>
<result><category>games-fps</category><package>industri</package><class>PkgMetadataXmlInvalidProjectError</class><msg>games-fps/industri metadata.xml &lt;maintainer/&gt; references invalid project 'games@gentoo.org'</msg></result>
<result><category>games-fps</category><package>legends</package><class>PkgMetadataXmlInvalidProjectError</class><msg>games-fps/legends metadata.xml &lt;maintainer/&gt; references invalid project 'games@gentoo.org'</msg></result>
<result><category>games-fps</category><package>lsdldoom</package><class>PkgMetadataXmlInvalidProjectError</class><msg>games-fps/lsdldoom metadata.xml &lt;maintainer/&gt; references invalid project 'games@gentoo.org'</msg></result>
<result><category>games-fps</category><package>nexuiz</package><class>PkgMetadataXmlInvalidProjectError</class><msg>games-fps/nexuiz metadata.xml &lt;maintainer/&gt; references invalid project 'games@gentoo.org'</msg></result>
<result><category>games-fps</category><package>openarena</package><class>PkgMetadataXmlInvalidProjectError</class><msg>games-fps/openarena metadata.xml &lt;maintainer/&gt; references invalid project 'games@gentoo.org'</msg></result>
<result><category>games-fps</category><package>postal2</package><class>PkgMetadataXmlInvalidProjectError</class><msg>games-fps/postal2 metadata.xml &lt;maintainer/&gt; references invalid project 'games@gentoo.org'</msg></result>
<result><category>games-fps</category><package>postal2mp-demo</package><class>PkgMetadataXmlInvalidProjectError</class><msg>games-fps/postal2mp-demo metadata.xml &lt;maintainer/&gt; references invalid project 'games@gentoo.org'</msg></result>
<result><category>games-fps</category><package>prboom</package><class>PkgMetadataXmlInvalidProjectError</class><msg>games-fps/prboom metadata.xml &lt;maintainer/&gt; references invalid project 'games@gentoo.org'</msg></result>
<result><category>games-fps</category><package>quake1-data</package><class>PkgMetadataXmlInvalidProjectError</class><msg>games-fps/quake1-data metadata.xml &lt;maintainer/&gt; references invalid project 'games@gentoo.org'</msg></result>
<result><category>games-fps</category><package>quake1-demodata</package><class>PkgMetadataXmlInvalidProjectError</class><msg>games-fps/quake1-demodata metadata.xml &lt;maintainer/&gt; references invalid project 'games@gentoo.org'</msg></result>
<result><category>games-fps</category><package>quake1-killer</package><class>PkgMetadataXmlInvalidProjectError</class><msg>games-fps/quake1-killer metadata.xml &lt;maintainer/&gt; references invalid project 'games@gentoo.org'</msg></result>
<result><category>games-fps</category><package>quake1-rally</package><class>PkgMetadataXmlInvalidProjectError</class><msg>games-fps/quake1-rally metadata.xml &lt;maintainer/&gt; references invalid project 'games@gentoo.org'</msg></result>
<result><category>games-fps</category><package>quake1-teamfortress</package><class>PkgMetadataXmlInvalidProjectError</class><msg>games-fps/quake1-teamfortress metadata.xml &lt;maintainer/&gt; references invalid project 'games@gentoo.org'</msg></result>
<result><category>games-fps</category><package>quake1-textures</package><class>PkgMetadataXmlInvalidProjectError</class><msg>games-fps/quake1-textures metadata.xml &lt;maintainer/&gt; references invalid project 'games@gentoo.org'</msg></result>
<result><category>games-fps</category><package>quake2-data</package><class>PkgMetadataXmlInvalidProjectError</class><msg>games-fps/quake2-data metadata.xml &lt;maintainer/&gt; references invalid project 'games@gentoo.org'</msg></result>
<result><category>games-fps</category><package>quake2-demodata</package><class>PkgMetadataXmlInvalidProjectError</class><msg>games-fps/quake2-demodata metadata.xml &lt;maintainer/&gt; references invalid project 'games@gentoo.org'</msg></result>
<result><category>games-fps</category><package>quake2-icculus</package><class>PkgMetadataXmlInvalidProjectError</class><msg>games-fps/quake2-icculus metadata.xml &lt;maintainer/&gt; references invalid project 'games@gentoo.org'</msg></result>
<result><category>games-fps</category><package>quake2-textures</package><class>PkgMetadataXmlInvalidProjectError</class><msg>games-fps/quake2-textures metadata.xml &lt;maintainer/&gt; references invalid project 'games@gentoo.org'</msg></result>
<result><category>games-fps</category><package>quake3</package><class>PkgMetadataXmlInvalidProjectError</class><msg>games-fps/quake3 metadata.xml &lt;maintainer/&gt; references invalid project 'games@gentoo.org'</msg></result>
<result><category>games-fps</category><package>quake3-alliance</package><class>PkgMetadataXmlInvalidProjectError</class><msg>games-fps/quake3-alliance metadata.xml &lt;maintainer/&gt; references invalid project 'games@gentoo.org'</msg></result>
<result><category>games-fps</category><package>quake3-alternatefire</package><class>PkgMetadataXmlInvalidProjectError</class><msg>games-fps/quake3-alternatefire metadata.xml &lt;maintainer/&gt; references invalid project 'games@gentoo.org'</msg></result>
<result><category>games-fps</category><package>quake3-bfp</package><class>PkgMetadataXmlInvalidProjectError</class><msg>games-fps/quake3-bfp metadata.xml &lt;maintainer/&gt; references invalid project 'games@gentoo.org'</msg></result>
<result><category>games-fps</category><package>quake3-bin</package><class>PkgMetadataXmlInvalidProjectError</class><msg>games-fps/quake3-bin metadata.xml &lt;maintainer/&gt; references invalid project 'games@gentoo.org'</msg></result>
<result><category>games-fps</category><package>quake3-cpma</package><class>PkgMetadataXmlInvalidProjectError</class><msg>games-fps/quake3-cpma metadata.xml &lt;maintainer/&gt; references invalid project 'games@gentoo.org'</msg></result>
<result><category>games-fps</category><package>quake3-data</package><class>PkgMetadataXmlInvalidProjectError</class><msg>games-fps/quake3-data metadata.xml &lt;maintainer/&gt; references invalid project 'games@gentoo.org'</msg></result>
<result><category>games-fps</category><package>quake3-defrag</package><class>PkgMetadataXmlInvalidProjectError</class><msg>games-fps/quake3-defrag metadata.xml &lt;maintainer/&gt; references invalid project 'games@gentoo.org'</msg></result>
<result><category>games-fps</category><package>quake3-demo</package><class>PkgMetadataXmlInvalidProjectError</class><msg>games-fps/quake3-demo metadata.xml &lt;maintainer/&gt; references invalid project 'games@gentoo.org'</msg></result>
<result><category>games-fps</category><package>quake3-excessiveplus</package><class>PkgMetadataXmlInvalidProjectError</class><msg>games-fps/quake3-excessiveplus metadata.xml &lt;maintainer/&gt; references invalid project 'games@gentoo.org'</msg></result>
<result><category>games-fps</category><package>quake3-lrctf</package><class>PkgMetadataXmlInvalidProjectError</class><msg>games-fps/quake3-lrctf metadata.xml &lt;maintainer/&gt; references invalid project 'games@gentoo.org'</msg></result>
<result><category>games-fps</category><package>quake3-matrix</package><class>PkgMetadataXmlInvalidProjectError</class><msg>games-fps/quake3-matrix metadata.xml &lt;maintainer/&gt; references invalid project 'games@gentoo.org'</msg></result>
<result><category>games-fps</category><package>quake3-nsco</package><class>PkgMetadataXmlInvalidProjectError</class><msg>games-fps/quake3-nsco metadata.xml &lt;maintainer/&gt; references invalid project 'games@gentoo.org'</msg></result>
<result><category>games-fps</category><package>quake3-osp</package><class>PkgMetadataXmlInvalidProjectError</class><msg>games-fps/quake3-osp metadata.xml &lt;maintainer/&gt; references invalid project 'games@gentoo.org'</msg></result>
<result><category>games-fps</category><package>quake3-ra3</package><class>PkgMetadataXmlInvalidProjectError</class><msg>games-fps/quake3-ra3 metadata.xml &lt;maintainer/&gt; references invalid project 'games@gentoo.org'</msg></result>
<result><category>games-fps</category><package>quake3-reaction</package><class>PkgMetadataXmlInvalidProjectError</class><msg>games-fps/quake3-reaction metadata.xml &lt;maintainer/&gt; references invalid project 'games@gentoo.org'</msg></result>
<result><category>games-fps</category><package>quake3-ruinhunters</package><class>PkgMetadataXmlInvalidProjectError</class><msg>games-fps/quake3-ruinhunters metadata.xml &lt;maintainer/&gt; references invalid project 'games@gentoo.org'</msg></result>
<result><category>games-fps</category><package>quake3-teamarena</package><class>PkgMetadataXmlInvalidProjectError</class><msg>games-fps/quake3-teamarena metadata.xml &lt;maintainer/&gt; references invalid project 'games@gentoo.org'</msg></result>
<result><category>games-fps</category><package>quake3-threewave</package><class>PkgMetadataXmlInvalidProjectError</class><msg>games-fps/quake3-threewave metadata.xml &lt;maintainer/&gt; references invalid project 'games@gentoo.org'</msg></result>
<result><category>games-fps</category><package>quake4-bin</package><class>PkgMetadataXmlInvalidProjectError</class><msg>games-fps/quake4-bin metadata.xml &lt;maintainer/&gt; references invalid project 'games@gentoo.org'</msg></result>
<result><category>games-fps</category><package>quake4-data</package><class>PkgMetadataXmlInvalidProjectError</class><msg>games-fps/quake4-data metadata.xml &lt;maintainer/&gt; references invalid project 'games@gentoo.org'</msg></result>
<result><category>games-fps</category><package>quake4-demo</package><class>PkgMetadataXmlInvalidProjectError</class><msg>games-fps/quake4-demo metadata.xml &lt;maintainer/&gt; references invalid project 'games@gentoo.org'</msg></result>
<result><category>games-fps</category><package>quakeforge</package><class>PkgMetadataXmlInvalidProjectError</class><msg>games-fps/quakeforge metadata.xml &lt;maintainer/&gt; references invalid project 'games@gentoo.org'</msg></result>
<result><category>games-fps</category><package>qudos</package><class>PkgMetadataXmlInvalidProjectError</class><msg>games-fps/qudos metadata.xml &lt;maintainer/&gt; references invalid project 'games@gentoo.org'</msg></result>
<result><category>games-fps</category><package>red-blue-quake2</package><class>PkgMetadataXmlInvalidProjectError</class><msg>games-fps/red-blue-quake2 metadata.xml &lt;maintainer/&gt; references invalid project 'games@gentoo.org'</msg></result>
<result><category>games-fps</category><package>rott</package><class>PkgMetadataXmlInvalidProjectError</class><msg>games-fps/rott metadata.xml &lt;maintainer/&gt; references invalid project 'games@gentoo.org'</msg></result>
<result><category>games-fps</category><package>rtcw</package><class>PkgMetadataXmlInvalidProjectError</class><msg>games-fps/rtcw metadata.xml &lt;maintainer/&gt; references invalid project 'games@gentoo.org'</msg></result>
<result><category>games-fps</category><package>rtcwmp-demo</package><class>PkgMetadataXmlInvalidProjectError</class><msg>games-fps/rtcwmp-demo metadata.xml &lt;maintainer/&gt; references invalid project 'games@gentoo.org'</msg></result>
<result><category>games-fps</category><package>rtcwsp-demo</package><class>PkgMetadataXmlInvalidProjectError</class><msg>games-fps/rtcwsp-demo metadata.xml &lt;maintainer/&gt; references invalid project 'games@gentoo.org'</msg></result>
<result><category>games-fps</category><package>sauerbraten</package><class>PkgMetadataXmlInvalidProjectError</class><msg>games-fps/sauerbraten metadata.xml &lt;maintainer/&gt; references invalid project 'games@gentoo.org'</msg></result>
<result><category>games-fps</category><package>soldieroffortune</package><class>PkgMetadataXmlInvalidProjectError</class><msg>games-fps/soldieroffortune metadata.xml &lt;maintainer/&gt; references invalid project 'games@gentoo.org'</msg></result>
<result><category>games-fps</category><package>soldieroffortune-demo</package><class>PkgMetadataXmlInvalidProjectError</class><msg>games-fps/soldieroffortune-demo metadata.xml &lt;maintainer/&gt; references invalid project 'games@gentoo.org'</msg></result>
<result><category>games-fps</category><package>tenebrae</package><class>PkgMetadataXmlInvalidProjectError</class><msg>games-fps/tenebrae metadata.xml &lt;maintainer/&gt; references invalid project 'games@gentoo.org'</msg></result>
<result><category>games-fps</category><package>transfusion-bin</package><class>PkgMetadataXmlInvalidProjectError</class><msg>games-fps/transfusion-bin metadata.xml &lt;maintainer/&gt; references invalid project 'games@gentoo.org'</msg></result>
<result><category>games-fps</category><package>tribes2</package><class>PkgMetadataXmlInvalidProjectError</class><msg>games-fps/tribes2 metadata.xml &lt;maintainer/&gt; references invalid project 'games@gentoo.org'</msg></result>
<result><category>games-fps</category><package>turtlearena</package><class>PkgMetadataXmlInvalidProjectError</class><msg>games-fps/turtlearena metadata.xml &lt;maintainer/&gt; references invalid project 'games@gentoo.org'</msg></result>
<result><category>games-fps</category><package>unreal</package><class>PkgMetadataXmlInvalidProjectError</class><msg>games-fps/unreal metadata.xml &lt;maintainer/&gt; references invalid project 'games@gentoo.org'</msg></result>
<result><category>games-fps</category><package>unreal-tournament</package><class>PkgMetadataXmlInvalidProjectError</class><msg>games-fps/unreal-tournament metadata.xml &lt;maintainer/&gt; references invalid project 'games@gentoo.org'</msg></result>
<result><category>games-fps</category><package>unreal-tournament-bonuspacks</package><class>PkgMetadataXmlInvalidProjectError</class><msg>games-fps/unreal-tournament-bonuspacks metadata.xml &lt;maintainer/&gt; references invalid project 'games@gentoo.org'</msg></result>
<result><category>games-fps</category><package>unreal-tournament-goty</package><class>PkgMetadataXmlInvalidProjectError</class><msg>games-fps/unreal-tournament-goty metadata.xml &lt;maintainer/&gt; references invalid project 'games@gentoo.org'</msg></result>
<result><category>games-fps</category><package>unreal-tournament-strikeforce</package><class>PkgMetadataXmlInvalidProjectError</class><msg>games-fps/unreal-tournament-strikeforce metadata.xml &lt;maintainer/&gt; references invalid project 'games@gentoo.org'</msg></result>
<result><category>games-fps</category><package>urbanterror</package><class>PkgMetadataXmlInvalidProjectError</class><msg>games-fps/urbanterror metadata.xml &lt;maintainer/&gt; references invalid project 'games@gentoo.org'</msg></result>
<result><category>games-fps</category><package>ut2003</package><class>PkgMetadataXmlInvalidProjectError</class><msg>games-fps/ut2003 metadata.xml &lt;maintainer/&gt; references invalid project 'games@gentoo.org'</msg></result>
<result><category>games-fps</category><package>ut2003-bonuspack-cm</package><class>PkgMetadataXmlInvalidProjectError</class><msg>games-fps/ut2003-bonuspack-cm metadata.xml &lt;maintainer/&gt; references invalid project 'games@gentoo.org'</msg></result>
<result><category>games-fps</category><package>ut2003-bonuspack-de</package><class>PkgMetadataXmlInvalidProjectError</class><msg>games-fps/ut2003-bonuspack-de metadata.xml &lt;maintainer/&gt; references invalid project 'games@gentoo.org'</msg></result>
<result><category>games-fps</category><package>ut2003-bonuspack-epic</package><class>PkgMetadataXmlInvalidProjectError</class><msg>games-fps/ut2003-bonuspack-epic metadata.xml &lt;maintainer/&gt; references invalid project 'games@gentoo.org'</msg></result>
<result><category>games-fps</category><package>ut2003-data</package><class>PkgMetadataXmlInvalidProjectError</class><msg>games-fps/ut2003-data metadata.xml &lt;maintainer/&gt; references invalid project 'games@gentoo.org'</msg></result>
<result><category>games-fps</category><package>ut2003-demo</package><class>PkgMetadataXmlInvalidProjectError</class><msg>games-fps/ut2003-demo metadata.xml &lt;maintainer/&gt; references invalid project 'games@gentoo.org'</msg></result>
<result><category>games-fps</category><package>ut2004</package><class>PkgMetadataXmlInvalidProjectError</class><msg>games-fps/ut2004 metadata.xml &lt;maintainer/&gt; references invalid project 'games@gentoo.org'</msg></result>
<result><category>games-fps</category><package>ut2004-action</package><class>PkgMetadataXmlInvalidProjectError</class><msg>games-fps/ut2004-action metadata.xml &lt;maintainer/&gt; references invalid project 'games@gentoo.org'</msg></result>
<result><category>games-fps</category><package>ut2004-airbuccaneers</package><class>PkgMetadataXmlInvalidProjectError</class><msg>games-fps/ut2004-airbuccaneers metadata.xml &lt;maintainer/&gt; references invalid project 'games@gentoo.org'</msg></result>
<result><category>games-fps</category><package>ut2004-bonuspack-cbp1</package><class>PkgMetadataXmlInvalidProjectError</class><msg>games-fps/ut2004-bonuspack-cbp1 metadata.xml &lt;maintainer/&gt; references invalid project 'games@gentoo.org'</msg></result>
<result><category>games-fps</category><package>ut2004-bonuspack-cbp2</package><class>PkgMetadataXmlInvalidProjectError</class><msg>games-fps/ut2004-bonuspack-cbp2 metadata.xml &lt;maintainer/&gt; references invalid project 'games@gentoo.org'</msg></result>
<result><category>games-fps</category><package>ut2004-bonuspack-ece</package><class>PkgMetadataXmlInvalidProjectError</class><msg>games-fps/ut2004-bonuspack-ece metadata.xml &lt;maintainer/&gt; references invalid project 'games@gentoo.org'</msg></result>
<result><category>games-fps</category><package>ut2004-bonuspack-mega</package><class>PkgMetadataXmlInvalidProjectError</class><msg>games-fps/ut2004-bonuspack-mega metadata.xml &lt;maintainer/&gt; references invalid project 'games@gentoo.org'</msg></result>
<result><category>games-fps</category><package>ut2004-cor</package><class>PkgMetadataXmlInvalidProjectError</class><msg>games-fps/ut2004-cor metadata.xml &lt;maintainer/&gt; references invalid project 'games@gentoo.org'</msg></result>
<result><category>games-fps</category><package>ut2004-crossfire</package><class>PkgMetadataXmlInvalidProjectError</class><msg>games-fps/ut2004-crossfire metadata.xml &lt;maintainer/&gt; references invalid project 'games@gentoo.org'</msg></result>
<result><category>games-fps</category><package>ut2004-data</package><class>PkgMetadataXmlInvalidProjectError</class><msg>games-fps/ut2004-data metadata.xml &lt;maintainer/&gt; references invalid project 'games@gentoo.org'</msg></result>
<result><category>games-fps</category><package>ut2004-deathball</package><class>PkgMetadataXmlInvalidProjectError</class><msg>games-fps/ut2004-deathball metadata.xml &lt;maintainer/&gt; references invalid project 'games@gentoo.org'</msg></result>
<result><category>games-fps</category><package>ut2004-demo</package><class>PkgMetadataXmlInvalidProjectError</class><msg>games-fps/ut2004-demo metadata.xml &lt;maintainer/&gt; references invalid project 'games@gentoo.org'</msg></result>
<result><category>games-fps</category><package>ut2004-fragops</package><class>PkgMetadataXmlInvalidProjectError</class><msg>games-fps/ut2004-fragops metadata.xml &lt;maintainer/&gt; references invalid project 'games@gentoo.org'</msg></result>
<result><category>games-fps</category><package>ut2004-hamsterbash</package><class>PkgMetadataXmlInvalidProjectError</class><msg>games-fps/ut2004-hamsterbash metadata.xml &lt;maintainer/&gt; references invalid project 'games@gentoo.org'</msg></result>
<result><category>games-fps</category><package>ut2004-muralis</package><class>PkgMetadataXmlInvalidProjectError</class><msg>games-fps/ut2004-muralis metadata.xml &lt;maintainer/&gt; references invalid project 'games@gentoo.org'</msg></result>
<result><category>games-fps</category><package>ut2004-strikeforce</package><class>PkgMetadataXmlInvalidProjectError</class><msg>games-fps/ut2004-strikeforce metadata.xml &lt;maintainer/&gt; references invalid project 'games@gentoo.org'</msg></result>
<result><category>games-fps</category><package>ut2004-troopers</package><class>PkgMetadataXmlInvalidProjectError</class><msg>games-fps/ut2004-troopers metadata.xml &lt;maintainer/&gt; references invalid project 'games@gentoo.org'</msg></result>
<result><category>games-fps</category><package>ut2004-unwheel</package><class>PkgMetadataXmlInvalidProjectError</class><msg>games-fps/ut2004-unwheel metadata.xml &lt;maintainer/&gt; references invalid project 'games@gentoo.org'</msg></result>
<result><category>games-fps</category><package>warsow</package><class>PkgMetadataXmlInvalidProjectError</class><msg>games-fps/warsow metadata.xml &lt;maintainer/&gt; references invalid project 'games@gentoo.org'</msg></result>
<result><category>games-fps</category><package>warsow-community-map-pack</package><class>PkgMetadataXmlInvalidProjectError</class><msg>games-fps/warsow-community-map-pack metadata.xml &lt;maintainer/&gt; references invalid project 'games@gentoo.org'</msg></result>
<result><category>games-fps</category><package>wolfgl</package><class>PkgMetadataXmlInvalidProjectError</class><msg>games-fps/wolfgl metadata.xml &lt;maintainer/&gt; references invalid project 'games@gentoo.org'</msg></result>
<result><category>games-fps</category><package>worldofpadman</package><class>PkgMetadataXmlInvalidProjectError</class><msg>games-fps/worldofpadman metadata.xml &lt;maintainer/&gt; references invalid project 'games@gentoo.org'</msg></result>
<result><category>games-fps</category><package>xonotic</package><class>PkgMetadataXmlInvalidProjectError</class><msg>games-fps/xonotic metadata.xml &lt;maintainer/&gt; references invalid project 'games@gentoo.org'</msg></result>
<result><category>net-firewall</category><package>arno-iptables-firewall</package><version>2.0.1e</version><class>NonExistentDeps</class><msg>depset rdepends: nonexistent dep: [ &lt;sys-apps/coreutils-8.20 ]</msg></result>
<result><category>net-firewall</category><package>conntrack-tools</package><version>1.4.3</version><class>DroppedKeyword</class><msg>keywords dropped: alpha</msg></result>
<result><category>net-firewall</category><package>firehol</package><version>3.0.1</version><class>DroppedKeyword</class><msg>keywords dropped: ppc, sparc, x86</msg></result>
<result><category>net-firewall</category><package>fwbuilder</package><version>5.3.6</version><class>DroppedKeyword</class><msg>keywords dropped: ppc</msg></result>
<result><category>net-firewall</category><package>iptables</package><class>ExecutableFile</class><msg>unnecessary executable bit: 'files/iptables.init'</msg></result>
<result><category>net-firewall</category><package>nftables</package><class>ExecutableFile</class><msg>unnecessary executable bit: 'files/libexec/nftables.sh'</msg></result>
<result><category>mate-extra</category><package>caja-dropbox</package><class>PkgMetadataXmlInvalidProjectError</class><msg>mate-extra/caja-dropbox metadata.xml &lt;maintainer/&gt; references invalid project 'mate@gentoo.org'</msg></result>
<result><category>mate-extra</category><package>caja-extensions</package><class>PkgMetadataXmlInvalidProjectError</class><msg>mate-extra/caja-extensions metadata.xml &lt;maintainer/&gt; references invalid project 'mate@gentoo.org'</msg></result>
<result><category>mate-extra</category><package>mate-calc</package><class>PkgMetadataXmlInvalidProjectError</class><msg>mate-extra/mate-calc metadata.xml &lt;maintainer/&gt; references invalid project 'mate@gentoo.org'</msg></result>
<result><category>mate-extra</category><package>mate-dialogs</package><class>PkgMetadataXmlInvalidProjectError</class><msg>mate-extra/mate-dialogs metadata.xml &lt;maintainer/&gt; references invalid project 'mate@gentoo.org'</msg></result>
<result><category>mate-extra</category><package>mate-indicator-applet</package><class>PkgMetadataXmlInvalidProjectError</class><msg>mate-extra/mate-indicator-applet metadata.xml &lt;maintainer/&gt; references invalid project 'mate@gentoo.org'</msg></result>
<result><category>mate-extra</category><package>mate-media</package><class>PkgMetadataXmlInvalidProjectError</class><msg>mate-extra/mate-media metadata.xml &lt;maintainer/&gt; references invalid project 'mate@gentoo.org'</msg></result>
<result><category>mate-extra</category><package>mate-netbook</package><class>PkgMetadataXmlInvalidProjectError</class><msg>mate-extra/mate-netbook metadata.xml &lt;maintainer/&gt; references invalid project 'mate@gentoo.org'</msg></result>
<result><category>mate-extra</category><package>mate-polkit</package><class>PkgMetadataXmlInvalidProjectError</class><msg>mate-extra/mate-polkit metadata.xml &lt;maintainer/&gt; references invalid project 'mate@gentoo.org'</msg></result>
<result><category>mate-extra</category><package>mate-power-manager</package><class>PkgMetadataXmlInvalidProjectError</class><msg>mate-extra/mate-power-manager metadata.xml &lt;maintainer/&gt; references invalid project 'mate@gentoo.org'</msg></result>
<result><category>mate-extra</category><package>mate-screensaver</package><class>PkgMetadataXmlInvalidProjectError</class><msg>mate-extra/mate-screensaver metadata.xml &lt;maintainer/&gt; references invalid project 'mate@gentoo.org'</msg></result>
<result><category>mate-extra</category><package>mate-sensors-applet</package><class>PkgMetadataXmlInvalidProjectError</class><msg>mate-extra/mate-sensors-applet metadata.xml &lt;maintainer/&gt; references invalid project 'mate@gentoo.org'</msg></result>
<result><category>mate-extra</category><package>mate-system-monitor</package><class>PkgMetadataXmlInvalidProjectError</class><msg>mate-extra/mate-system-monitor metadata.xml &lt;maintainer/&gt; references invalid project 'mate@gentoo.org'</msg></result>
<result><category>mate-extra</category><package>mate-user-guide</package><class>PkgMetadataXmlInvalidProjectError</class><msg>mate-extra/mate-user-guide metadata.xml &lt;maintainer/&gt; references invalid project 'mate@gentoo.org'</msg></result>
<result><category>mate-extra</category><package>mate-user-share</package><class>PkgMetadataXmlInvalidProjectError</class><msg>mate-extra/mate-user-share metadata.xml &lt;maintainer/&gt; references invalid project 'mate@gentoo.org'</msg></result>
<result><category>mate-extra</category><package>mate-utils</package><class>PkgMetadataXmlInvalidProjectError</class><msg>mate-extra/mate-utils metadata.xml &lt;maintainer/&gt; references invalid project 'mate@gentoo.org'</msg></result>
<result><category>lxde-base</category><package>lxappearance</package><class>PkgMetadataXmlInvalidProjectError</class><msg>lxde-base/lxappearance metadata.xml &lt;maintainer/&gt; references invalid project 'lxde@gentoo.org'</msg></result>
<result><category>lxde-base</category><package>lxappearance-obconf</package><class>PkgMetadataXmlInvalidProjectError</class><msg>lxde-base/lxappearance-obconf metadata.xml &lt;maintainer/&gt; references invalid project 'lxde@gentoo.org'</msg></result>
<result><category>lxde-base</category><package>lxde-common</package><class>PkgMetadataXmlInvalidProjectError</class><msg>lxde-base/lxde-common metadata.xml &lt;maintainer/&gt; references invalid project 'lxde@gentoo.org'</msg></result>
<result><category>lxde-base</category><package>lxde-icon-theme</package><class>PkgMetadataXmlInvalidProjectError</class><msg>lxde-base/lxde-icon-theme metadata.xml &lt;maintainer/&gt; references invalid project 'lxde@gentoo.org'</msg></result>
<result><category>lxde-base</category><package>lxde-meta</package><class>PkgMetadataXmlInvalidProjectError</class><msg>lxde-base/lxde-meta metadata.xml &lt;maintainer/&gt; references invalid project 'lxde@gentoo.org'</msg></result>
<result><category>lxde-base</category><package>lxde-meta</package><version>0.5.5-r4</version><class>NonExistentDeps</class><msg>depset rdepends: nonexistent dep: [ &lt;=lxde-base/lxsession-0.4.6.1 ]</msg></result>
<result><category>lxde-base</category><package>lxdm</package><class>PkgMetadataXmlInvalidProjectError</class><msg>lxde-base/lxdm metadata.xml &lt;maintainer/&gt; references invalid project 'lxde@gentoo.org'</msg></result>
<result><category>lxde-base</category><package>lxinput</package><class>PkgMetadataXmlInvalidProjectError</class><msg>lxde-base/lxinput metadata.xml &lt;maintainer/&gt; references invalid project 'lxde@gentoo.org'</msg></result>
<result><category>lxde-base</category><package>lxlauncher</package><class>PkgMetadataXmlInvalidProjectError</class><msg>lxde-base/lxlauncher metadata.xml &lt;maintainer/&gt; references invalid project 'lxde@gentoo.org'</msg></result>
<result><category>lxde-base</category><package>lxmenu-data</package><class>PkgMetadataXmlInvalidProjectError</class><msg>lxde-base/lxmenu-data metadata.xml &lt;maintainer/&gt; references invalid project 'lxde@gentoo.org'</msg></result>
<result><category>lxde-base</category><package>lxpanel</package><class>PkgMetadataXmlInvalidProjectError</class><msg>lxde-base/lxpanel metadata.xml &lt;maintainer/&gt; references invalid project 'lxde@gentoo.org'</msg></result>
<result><category>lxde-base</category><package>lxrandr</package><class>PkgMetadataXmlInvalidProjectError</class><msg>lxde-base/lxrandr metadata.xml &lt;maintainer/&gt; references invalid project 'lxde@gentoo.org'</msg></result>
<result><category>lxde-base</category><package>lxsession</package><class>PkgMetadataXmlInvalidProjectError</class><msg>lxde-base/lxsession metadata.xml &lt;maintainer/&gt; references invalid project 'lxde@gentoo.org'</msg></result>
<result><category>lxde-base</category><package>lxsession-edit</package><class>PkgMetadataXmlInvalidProjectError</class><msg>lxde-base/lxsession-edit metadata.xml &lt;maintainer/&gt; references invalid project 'lxde@gentoo.org'</msg></result>
<result><category>lxde-base</category><package>lxshortcut</package><class>PkgMetadataXmlInvalidProjectError</class><msg>lxde-base/lxshortcut metadata.xml &lt;maintainer/&gt; references invalid project 'lxde@gentoo.org'</msg></result>
<result><category>lxde-base</category><package>lxtask</package><class>PkgMetadataXmlInvalidProjectError</class><msg>lxde-base/lxtask metadata.xml &lt;maintainer/&gt; references invalid project 'lxde@gentoo.org'</msg></result>
<result><category>lxde-base</category><package>lxtask</package><version>0.1.6</version><class>DroppedKeyword</class><msg>keywords dropped: arm64</msg></result>
<result><category>lxde-base</category><package>lxterminal</package><class>PkgMetadataXmlInvalidProjectError</class><msg>lxde-base/lxterminal metadata.xml &lt;maintainer/&gt; references invalid project 'lxde@gentoo.org'</msg></result>
<result><category>lxde-base</category><package>lxterminal</package><version>0.2.0-r1</version><class>DroppedKeyword</class><msg>keywords dropped: arm64</msg></result>
<result><category>lxde-base</category><package>menu-cache</package><class>PkgMetadataXmlInvalidProjectError</class><msg>lxde-base/menu-cache metadata.xml &lt;maintainer/&gt; references invalid project 'lxde@gentoo.org'</msg></result>
</checks>
